makeh/__init__.py
makeh/__main__.py
makeh-0.3.1.dist-info/entry_points.txt
makeh-0.3.1.dist-info/LICENSE
makeh-0.3.1.dist-info/WHEEL
makeh-0.3.1.dist-info/METADATA
makeh-0.3.1.dist-info/RECORD
